MANIFEST.in
README.rst
setup.py
memorised/__init__.py
memorised/compat.py
memorised/decorators.py
memorised/tests.py
memorised.egg-info/PKG-INFO
memorised.egg-info/SOURCES.txt
memorised.egg-info/dependency_links.txt
memorised.egg-info/requires.txt
memorised.egg-info/top_level.txt