Metadata-Version: 1.1
Name: memorised
Version: 1.1.0
Summary: memcache memoization decorators and utils for python
Home-page: http://github.com/1stvamp/memorised/
Author: Wes Mason
Author-email: wes@1stvamp.org
License: BSD
Platform: UNKNOWN
Classifier: Programming Language :: Python
Classifier: Programming Language :: Python :: 2
Classifier: Programming Language :: Python :: 2.6
Classifier: Programming Language :: Python :: 2.7
Classifier: Programming Language :: Python :: 3
Classifier: Programming Language :: Python :: 3.2
Classifier: Programming Language :: Python :: 3.3
Classifier: Programming Language :: Python :: 3.4
